SearchableTree/__init__.py
SearchableTree-1.0.4.dist-info/LICENSE
SearchableTree-1.0.4.dist-info/METADATA
SearchableTree-1.0.4.dist-info/WHEEL
SearchableTree-1.0.4.dist-info/top_level.txt
SearchableTree-1.0.4.dist-info/RECORD
