Metadata-Version: 2.1
Name: SearchableTree
Version: 1.0.4
Summary: Simple tree struct with search and traversal utilities
Author-email: Spin <pnspin@gmail.com>
Project-URL: Repository, https://github.com/pnspin/SearchableTree
License-File: LICENSE
